{
  "manifest_version": 1,
  "entities": [
    {"key":"industry_chain:ai_compute_infrastructure","entity_type":"industry_chain","layer_code":"industry_chain","name":"AI算力基础设施","canonical_name":"AI算力基础设施","aliases":["AI Compute Infrastructure"],"status":"active","profile":{"chain_code":"ai_compute_infrastructure","definition":"支撑AI训练与推理计算的芯片、封装、服务器、网络、存储、供电、冷却和数据中心静态产业链。","boundary_note":"不包含动态电力价格、云服务收入或推理结论。","scope_type":"global","version":1,"review_status":"approved","source_name":"IEA Energy and AI; NVIDIA Data Center Architecture","source_url":"https://www.iea.org/reports/energy-and-ai/energy-demand-from-ai","verified_at":"2026-07-12T00:00:00Z"}},
    {"key":"industry_chain:semiconductor_manufacturing","entity_type":"industry_chain","layer_code":"industry_chain","name":"半导体制造","canonical_name":"半导体制造","aliases":["Semiconductor Manufacturing"],"status":"active","profile":{"chain_code":"semiconductor_manufacturing","definition":"从集成电路设计、材料与设备输入到晶圆制造、先进封装、测试和集成电路成品的静态产业链。","boundary_note":"不包含当前产能紧张程度、市场份额或投资结论。","scope_type":"global","version":1,"review_status":"approved","source_name":"SEMI Semiconductor Manufacturing Process","source_url":"https://www.semi.org/en/ehs_PFAS/mfg_markets_overview","verified_at":"2026-07-12T00:00:00Z"}},
    {"key":"chain_node:rack_power_system","entity_type":"chain_node","layer_code":"industry_chain","name":"机架级供电系统","canonical_name":"机架级供电系统","aliases":["Rack-scale Power System"],"status":"active","profile":{"chain_position":"infrastructure","node_category":"equipment","definition":"从设施输入到AI机架的变换、配电、备电与控制系统。","unit_of_analysis":"system","granularity_note":"与外部电网、发电及芯片电源器件分开。"}},
    {"key":"chain_node:liquid_cooling_system","entity_type":"chain_node","layer_code":"industry_chain","name":"液冷系统","canonical_name":"液冷系统","aliases":["Liquid Cooling System"],"status":"active","profile":{"chain_position":"infrastructure","node_category":"infrastructure","definition":"面向高功率密度IT设备的液体传热、换热与循环系统。","unit_of_analysis":"system","granularity_note":"以机架或设施冷却系统为分析单位。"}},
    {"key":"chain_node:ai_storage_system","entity_type":"chain_node","layer_code":"industry_chain","name":"AI存储系统","canonical_name":"AI存储系统","aliases":["AI Storage System"],"status":"active","profile":{"chain_position":"infrastructure","node_category":"infrastructure","definition":"支撑训练数据摄取、checkpoint与推理数据访问的存储系统。","unit_of_analysis":"system","granularity_note":"不与HBM或服务器内存合并。"}},
    {"key":"chain_node:data_center_networking","entity_type":"chain_node","layer_code":"industry_chain","name":"数据中心网络","canonical_name":"数据中心网络","aliases":["Data Center Networking"],"status":"active","profile":{"chain_position":"infrastructure","node_category":"infrastructure","definition":"连接机架、存储和集群的scale-out及前端网络系统。","unit_of_analysis":"system","granularity_note":"与机架内scale-up互连分开。"}},
    {"key":"chain_node:optical_interconnect","entity_type":"chain_node","layer_code":"industry_chain","name":"光互连","canonical_name":"光互连","aliases":["Optical Interconnect"],"status":"active","profile":{"chain_position":"midstream","node_category":"component","definition":"数据中心内以光器件和光链路承载高速互连的技术单元。","unit_of_analysis":"component","granularity_note":"保持光链路或模块层，不下钻激光器和DSP。"}},
    {"key":"chain_node:scale_up_interconnect","entity_type":"chain_node","layer_code":"industry_chain","name":"规模扩展互连","canonical_name":"规模扩展互连","aliases":["Scale-up Interconnect"],"status":"active","profile":{"chain_position":"midstream","node_category":"component","definition":"机架内GPU或加速器之间的高带宽低时延互连。","unit_of_analysis":"system","granularity_note":"与scale-out数据中心网络分开。"}},
    {"key":"chain_node:hbm","entity_type":"chain_node","layer_code":"industry_chain","name":"高带宽内存","canonical_name":"高带宽内存","aliases":["High-bandwidth Memory","HBM"],"status":"active","profile":{"chain_position":"midstream","node_category":"component","definition":"与AI加速器近封装并提供高带宽访问的堆叠内存。","unit_of_analysis":"component","granularity_note":"与普通DRAM和SSD分开。"}},
    {"key":"chain_node:advanced_packaging","entity_type":"chain_node","layer_code":"industry_chain","name":"先进封装","canonical_name":"先进封装","aliases":["Advanced Packaging"],"status":"active","profile":{"chain_position":"midstream","node_category":"process","definition":"通过interposer、2.5D或3D integration集成逻辑芯片、HBM与互连的制造环节。","unit_of_analysis":"process","granularity_note":"制造过程级，不绑定单一厂商品牌。"}},
    {"key":"chain_node:ai_server","entity_type":"chain_node","layer_code":"industry_chain","name":"AI服务器","canonical_name":"AI服务器","aliases":["AI Server"],"status":"active","profile":{"chain_position":"downstream","node_category":"product","definition":"集成加速器、CPU、内存、网络、存储及供电冷却接口的计算系统。","unit_of_analysis":"system","granularity_note":"服务器或compute tray级，不等同数据中心。"}},
    {"key":"chain_node:integrated_circuit_design","entity_type":"chain_node","layer_code":"industry_chain","name":"集成电路设计","canonical_name":"集成电路设计","aliases":["Integrated Circuit Design"],"status":"active","profile":{"chain_position":"upstream","node_category":"process","definition":"将产品需求转化为经过设计、验证并可交付制造准备数据的集成电路设计活动。","unit_of_analysis":"process","granularity_note":"设计活动级，不等同EDA工具，也不绑定fabless公司。"}},
    {"key":"chain_node:semiconductor_silicon_wafer","entity_type":"chain_node","layer_code":"industry_chain","name":"半导体硅片","canonical_name":"半导体硅片","aliases":["Semiconductor Silicon Wafer"],"status":"active","profile":{"chain_position":"upstream","node_category":"material","definition":"承载晶圆制造工艺的半导体级硅衬底。","unit_of_analysis":"material","granularity_note":"不复用光伏多晶硅商品节点。"}},
    {"key":"chain_node:photoresist","entity_type":"chain_node","layer_code":"industry_chain","name":"光刻胶","canonical_name":"光刻胶","aliases":["Photoresist"],"status":"active","profile":{"chain_position":"upstream","node_category":"material","definition":"在光刻曝光和显影中形成图形的感光材料。","unit_of_analysis":"material","granularity_note":"保持材料级，不拆具体配方。"}},
    {"key":"chain_node:electronic_specialty_gases","entity_type":"chain_node","layer_code":"industry_chain","name":"电子特气","canonical_name":"电子特气","aliases":["Electronic Specialty Gases"],"status":"active","profile":{"chain_position":"upstream","node_category":"material","definition":"用于沉积、刻蚀、掺杂等晶圆工艺的高纯气体集合。","unit_of_analysis":"material","granularity_note":"按电子级特气集合，后续可再拆具体气体。"}},
    {"key":"chain_node:deposition_equipment","entity_type":"chain_node","layer_code":"industry_chain","name":"薄膜沉积设备","canonical_name":"薄膜沉积设备","aliases":["Thin-film Deposition Equipment"],"status":"active","profile":{"chain_position":"midstream","node_category":"equipment","definition":"在晶圆表面形成介质、金属或外延薄膜的设备。","unit_of_analysis":"equipment","granularity_note":"按工艺设备族，不拆ALD、CVD或PVD。"}},
    {"key":"chain_node:etch_equipment","entity_type":"chain_node","layer_code":"industry_chain","name":"刻蚀设备","canonical_name":"刻蚀设备","aliases":["Etch Equipment"],"status":"active","profile":{"chain_position":"midstream","node_category":"equipment","definition":"选择性移除晶圆材料并形成结构的制造设备。","unit_of_analysis":"equipment","granularity_note":"按设备族，不拆具体刻蚀类别。"}},
    {"key":"chain_node:ion_implantation_equipment","entity_type":"chain_node","layer_code":"industry_chain","name":"离子注入设备","canonical_name":"离子注入设备","aliases":["Ion Implantation Equipment"],"status":"active","profile":{"chain_position":"midstream","node_category":"equipment","definition":"向晶圆材料引入受控掺杂离子的设备。","unit_of_analysis":"equipment","granularity_note":"单一关键工艺设备族。"}},
    {"key":"chain_node:cmp_equipment","entity_type":"chain_node","layer_code":"industry_chain","name":"CMP设备","canonical_name":"CMP设备","aliases":["Chemical Mechanical Planarization Equipment"],"status":"active","profile":{"chain_position":"midstream","node_category":"equipment","definition":"通过化学机械作用实现晶圆表面平坦化的设备。","unit_of_analysis":"equipment","granularity_note":"设备级，CMP材料后续另审。"}},
    {"key":"chain_node:metrology_inspection_equipment","entity_type":"chain_node","layer_code":"industry_chain","name":"量测与缺陷检测设备","canonical_name":"量测与缺陷检测设备","aliases":["Metrology and Inspection Equipment"],"status":"active","profile":{"chain_position":"midstream","node_category":"equipment","definition":"测量关键尺寸并发现晶圆缺陷，为工艺控制提供反馈的设备。","unit_of_analysis":"equipment","granularity_note":"首版合并metrology与inspection。"}},
    {"key":"chain_node:wafer_fabrication","entity_type":"chain_node","layer_code":"industry_chain","name":"晶圆制造","canonical_name":"晶圆制造","aliases":["Wafer Fabrication"],"status":"active","profile":{"chain_position":"midstream","node_category":"process","definition":"在晶圆上重复执行成膜、光刻、刻蚀、掺杂、平坦化与检测的前道制造过程。","unit_of_analysis":"process","granularity_note":"fab process总体环节，具体设备保留独立节点。"}},
    {"key":"chain_node:semiconductor_testing","entity_type":"chain_node","layer_code":"industry_chain","name":"半导体测试","canonical_name":"半导体测试","aliases":["Semiconductor Testing"],"status":"active","profile":{"chain_position":"downstream","node_category":"process","definition":"对晶圆或封装后器件执行电性、功能和可靠性测试的制造环节。","unit_of_analysis":"process","granularity_note":"首版合并wafer test与final test。"}},
    {"key":"chain_node:integrated_circuit","entity_type":"chain_node","layer_code":"industry_chain","name":"集成电路成品","canonical_name":"集成电路成品","aliases":["Integrated Circuit"],"status":"active","profile":{"chain_position":"downstream","node_category":"product","definition":"完成制造、封装和测试后可进入电子系统的芯片产品。","unit_of_analysis":"product","granularity_note":"通用产出，不用GPU代表全部半导体产品。"}}
  ],
  "profiles": [
    {"entity_key":"chain_node:power_grid","entity_type":"chain_node","data":{"chain_position":"infrastructure","node_category":"infrastructure","definition":"向数据中心提供外部输配电与并网能力的基础设施。","unit_of_analysis":"system","granularity_note":"与发电、电力商品及机架内供电分开。"}},
    {"entity_key":"chain_node:data_center","entity_type":"chain_node","data":{"chain_position":"infrastructure","node_category":"infrastructure","definition":"容纳服务器、存储、网络及供电冷却设施的物理场所。","unit_of_analysis":"system","granularity_note":"保持设施级，不拆到单栋园区。"}},
    {"entity_key":"chain_node:gpu","entity_type":"chain_node","data":{"chain_position":"midstream","node_category":"component","definition":"执行并行AI训练与推理计算的加速处理器。","unit_of_analysis":"component","granularity_note":"芯片级，不绑定单一厂商或型号。"}},
    {"entity_key":"chain_node:eda","entity_type":"chain_node","data":{"chain_position":"upstream","node_category":"service","definition":"用于集成电路设计、验证、实现和制造准备的软件工具体系。","unit_of_analysis":"service","granularity_note":"领域工具体系级，不拆单个软件模块。"}},
    {"entity_key":"chain_node:lithography_machine","entity_type":"chain_node","data":{"chain_position":"midstream","node_category":"equipment","definition":"将芯片图形投射到晶圆上的DUV或EUV制造系统。","unit_of_analysis":"equipment","granularity_note":"设备平台级，不拆具体型号。"}}
  ],
  "industry_chain_memberships": [
    {"id":"membership:ai:power_grid","industry_chain_key":"industry_chain:ai_compute_infrastructure","chain_node_key":"chain_node:power_grid","stage_code":"infrastructure","role_code":"infrastructure","stage_order":10,"is_core":true,"source_name":"IEA Energy and AI","source_url":"https://www.iea.org/reports/energy-and-ai/energy-demand-from-ai","verified_at":"2026-07-12T00:00:00Z","status":"active"},
    {"id":"membership:ai:rack_power_system","industry_chain_key":"industry_chain:ai_compute_infrastructure","chain_node_key":"chain_node:rack_power_system","stage_code":"infrastructure","role_code":"equipment","stage_order":20,"is_core":true,"source_name":"Open Compute Project Rack and Power","source_url":"https://www.opencompute.org/index.php/community/rack-and-power","verified_at":"2026-07-12T00:00:00Z","status":"active"},
    {"id":"membership:ai:liquid_cooling_system","industry_chain_key":"industry_chain:ai_compute_infrastructure","chain_node_key":"chain_node:liquid_cooling_system","stage_code":"infrastructure","role_code":"infrastructure","stage_order":30,"is_core":true,"source_name":"ASHRAE Data Center Resources","source_url":"https://www.ashrae.org/technical-resources/bookstore/datacom-series","verified_at":"2026-07-12T00:00:00Z","status":"active"},
    {"id":"membership:ai:data_center","industry_chain_key":"industry_chain:ai_compute_infrastructure","chain_node_key":"chain_node:data_center","stage_code":"infrastructure","role_code":"infrastructure","stage_order":40,"is_core":true,"source_name":"NVIDIA Data Center Architecture","source_url":"https://docs.nvidia.com/ncx/ncp-software-reference-guide/latest/data-center-architecture.html","verified_at":"2026-07-12T00:00:00Z","status":"active"},
    {"id":"membership:ai:advanced_packaging","industry_chain_key":"industry_chain:ai_compute_infrastructure","chain_node_key":"chain_node:advanced_packaging","stage_code":"midstream","role_code":"process","stage_order":50,"is_core":true,"source_name":"TSMC CoWoS","source_url":"https://3dfabric.tsmc.com/english/dedicatedFoundry/technology/cowos.htm","verified_at":"2026-07-12T00:00:00Z","status":"active"},
    {"id":"membership:ai:hbm","industry_chain_key":"industry_chain:ai_compute_infrastructure","chain_node_key":"chain_node:hbm","stage_code":"midstream","role_code":"component","stage_order":60,"is_core":true,"source_name":"Micron HBM","source_url":"https://www.micron.com/products/memory/hbm","verified_at":"2026-07-12T00:00:00Z","status":"active"},
    {"id":"membership:ai:gpu","industry_chain_key":"industry_chain:ai_compute_infrastructure","chain_node_key":"chain_node:gpu","stage_code":"midstream","role_code":"component","stage_order":70,"is_core":true,"source_name":"NVIDIA MGX Platform","source_url":"https://www.nvidia.com/en-us/data-center/products/mgx/","verified_at":"2026-07-12T00:00:00Z","status":"active"},
    {"id":"membership:ai:scale_up_interconnect","industry_chain_key":"industry_chain:ai_compute_infrastructure","chain_node_key":"chain_node:scale_up_interconnect","stage_code":"midstream","role_code":"component","stage_order":80,"is_core":true,"source_name":"NVIDIA NVLink","source_url":"https://www.nvidia.com/en-eu/data-center/nvlink/","verified_at":"2026-07-12T00:00:00Z","status":"active"},
    {"id":"membership:ai:data_center_networking","industry_chain_key":"industry_chain:ai_compute_infrastructure","chain_node_key":"chain_node:data_center_networking","stage_code":"infrastructure","role_code":"infrastructure","stage_order":90,"is_core":true,"source_name":"NVIDIA Data Center Architecture","source_url":"https://docs.nvidia.com/ncx/ncp-software-reference-guide/latest/data-center-architecture.html","verified_at":"2026-07-12T00:00:00Z","status":"active"},
    {"id":"membership:ai:optical_interconnect","industry_chain_key":"industry_chain:ai_compute_infrastructure","chain_node_key":"chain_node:optical_interconnect","stage_code":"midstream","role_code":"component","stage_order":100,"is_core":false,"source_name":"NVIDIA Data Center Architecture","source_url":"https://docs.nvidia.com/ncx/ncp-software-reference-guide/latest/data-center-architecture.html","verified_at":"2026-07-12T00:00:00Z","status":"active"},
    {"id":"membership:ai:ai_storage_system","industry_chain_key":"industry_chain:ai_compute_infrastructure","chain_node_key":"chain_node:ai_storage_system","stage_code":"infrastructure","role_code":"infrastructure","stage_order":110,"is_core":false,"source_name":"NVIDIA Data Center Architecture","source_url":"https://docs.nvidia.com/ncx/ncp-software-reference-guide/latest/data-center-architecture.html","verified_at":"2026-07-12T00:00:00Z","status":"active"},
    {"id":"membership:ai:ai_server","industry_chain_key":"industry_chain:ai_compute_infrastructure","chain_node_key":"chain_node:ai_server","stage_code":"downstream","role_code":"product","stage_order":120,"is_core":true,"source_name":"NVIDIA MGX Platform","source_url":"https://www.nvidia.com/en-us/data-center/products/mgx/","verified_at":"2026-07-12T00:00:00Z","status":"active"},
    {"id":"membership:semi:eda","industry_chain_key":"industry_chain:semiconductor_manufacturing","chain_node_key":"chain_node:eda","stage_code":"upstream","role_code":"service","stage_order":10,"is_core":true,"source_name":"Synopsys Silicon Design","source_url":"https://www.synopsys.com/silicon-design.html","verified_at":"2026-07-12T00:00:00Z","status":"active"},
    {"id":"membership:semi:integrated_circuit_design","industry_chain_key":"industry_chain:semiconductor_manufacturing","chain_node_key":"chain_node:integrated_circuit_design","stage_code":"upstream","role_code":"process","stage_order":20,"is_core":true,"source_name":"Synopsys Silicon Design","source_url":"https://www.synopsys.com/silicon-design.html","verified_at":"2026-07-12T00:00:00Z","status":"active"},
    {"id":"membership:semi:semiconductor_silicon_wafer","industry_chain_key":"industry_chain:semiconductor_manufacturing","chain_node_key":"chain_node:semiconductor_silicon_wafer","stage_code":"upstream","role_code":"material","stage_order":30,"is_core":true,"source_name":"SEMI Manufacturing Process","source_url":"https://www.semi.org/en/ehs_PFAS/mfg_markets_overview","verified_at":"2026-07-12T00:00:00Z","status":"active"},
    {"id":"membership:semi:photoresist","industry_chain_key":"industry_chain:semiconductor_manufacturing","chain_node_key":"chain_node:photoresist","stage_code":"upstream","role_code":"material","stage_order":40,"is_core":true,"source_name":"SEMI Manufacturing Process","source_url":"https://www.semi.org/en/ehs_PFAS/mfg_markets_overview","verified_at":"2026-07-12T00:00:00Z","status":"active"},
    {"id":"membership:semi:electronic_specialty_gases","industry_chain_key":"industry_chain:semiconductor_manufacturing","chain_node_key":"chain_node:electronic_specialty_gases","stage_code":"upstream","role_code":"material","stage_order":50,"is_core":true,"source_name":"SEMI Manufacturing Process","source_url":"https://www.semi.org/en/ehs_PFAS/mfg_markets_overview","verified_at":"2026-07-12T00:00:00Z","status":"active"},
    {"id":"membership:semi:lithography_machine","industry_chain_key":"industry_chain:semiconductor_manufacturing","chain_node_key":"chain_node:lithography_machine","stage_code":"midstream","role_code":"equipment","stage_order":60,"is_core":true,"source_name":"ASML Products","source_url":"https://www.asml.com/en/products","verified_at":"2026-07-12T00:00:00Z","status":"active"},
    {"id":"membership:semi:deposition_equipment","industry_chain_key":"industry_chain:semiconductor_manufacturing","chain_node_key":"chain_node:deposition_equipment","stage_code":"midstream","role_code":"equipment","stage_order":70,"is_core":true,"source_name":"Applied Materials Products","source_url":"https://www.appliedmaterials.com/eu/en/semiconductor/products.html","verified_at":"2026-07-12T00:00:00Z","status":"active"},
    {"id":"membership:semi:etch_equipment","industry_chain_key":"industry_chain:semiconductor_manufacturing","chain_node_key":"chain_node:etch_equipment","stage_code":"midstream","role_code":"equipment","stage_order":80,"is_core":true,"source_name":"Applied Materials Products","source_url":"https://www.appliedmaterials.com/eu/en/semiconductor/products.html","verified_at":"2026-07-12T00:00:00Z","status":"active"},
    {"id":"membership:semi:ion_implantation_equipment","industry_chain_key":"industry_chain:semiconductor_manufacturing","chain_node_key":"chain_node:ion_implantation_equipment","stage_code":"midstream","role_code":"equipment","stage_order":90,"is_core":false,"source_name":"Applied Materials Products","source_url":"https://www.appliedmaterials.com/eu/en/semiconductor/products.html","verified_at":"2026-07-12T00:00:00Z","status":"active"},
    {"id":"membership:semi:cmp_equipment","industry_chain_key":"industry_chain:semiconductor_manufacturing","chain_node_key":"chain_node:cmp_equipment","stage_code":"midstream","role_code":"equipment","stage_order":100,"is_core":false,"source_name":"Applied Materials Products","source_url":"https://www.appliedmaterials.com/eu/en/semiconductor/products.html","verified_at":"2026-07-12T00:00:00Z","status":"active"},
    {"id":"membership:semi:metrology_inspection_equipment","industry_chain_key":"industry_chain:semiconductor_manufacturing","chain_node_key":"chain_node:metrology_inspection_equipment","stage_code":"midstream","role_code":"equipment","stage_order":110,"is_core":true,"source_name":"KLA Wafer Inspection","source_url":"https://bbp.kla.com/","verified_at":"2026-07-12T00:00:00Z","status":"active"},
    {"id":"membership:semi:wafer_fabrication","industry_chain_key":"industry_chain:semiconductor_manufacturing","chain_node_key":"chain_node:wafer_fabrication","stage_code":"midstream","role_code":"process","stage_order":120,"is_core":true,"source_name":"SEMI Manufacturing Process","source_url":"https://www.semi.org/en/ehs_PFAS/mfg_markets_overview","verified_at":"2026-07-12T00:00:00Z","status":"active"},
    {"id":"membership:semi:advanced_packaging","industry_chain_key":"industry_chain:semiconductor_manufacturing","chain_node_key":"chain_node:advanced_packaging","stage_code":"downstream","role_code":"process","stage_order":130,"is_core":true,"source_name":"TSMC CoWoS","source_url":"https://3dfabric.tsmc.com/english/dedicatedFoundry/technology/cowos.htm","verified_at":"2026-07-12T00:00:00Z","status":"active"},
    {"id":"membership:semi:semiconductor_testing","industry_chain_key":"industry_chain:semiconductor_manufacturing","chain_node_key":"chain_node:semiconductor_testing","stage_code":"downstream","role_code":"process","stage_order":140,"is_core":true,"source_name":"SEMI Manufacturing Process","source_url":"https://www.semi.org/en/ehs_PFAS/mfg_markets_overview","verified_at":"2026-07-12T00:00:00Z","status":"active"},
    {"id":"membership:semi:integrated_circuit","industry_chain_key":"industry_chain:semiconductor_manufacturing","chain_node_key":"chain_node:integrated_circuit","stage_code":"downstream","role_code":"product","stage_order":150,"is_core":true,"source_name":"SEMI Manufacturing Process","source_url":"https://www.semi.org/en/ehs_PFAS/mfg_markets_overview","verified_at":"2026-07-12T00:00:00Z","status":"active"}
  ],
  "industry_chain_topology_edges": [
    {"id":"topology:ai:gpu_to_advanced_packaging","industry_chain_key":"industry_chain:ai_compute_infrastructure","from_chain_node_key":"chain_node:gpu","to_chain_node_key":"chain_node:advanced_packaging","relation_type":"supplies_to","evidence_note":"GPU die或logic作为先进封装集成对象。","source_name":"TSMC CoWoS","source_url":"https://3dfabric.tsmc.com/english/dedicatedFoundry/technology/cowos.htm","verified_at":"2026-07-12T00:00:00Z","status":"active"},
    {"id":"topology:ai:hbm_to_advanced_packaging","industry_chain_key":"industry_chain:ai_compute_infrastructure","from_chain_node_key":"chain_node:hbm","to_chain_node_key":"chain_node:advanced_packaging","relation_type":"supplies_to","evidence_note":"HBM stack作为先进封装集成对象。","source_name":"Micron HBM; TSMC CoWoS","source_url":"https://www.micron.com/products/memory/hbm","verified_at":"2026-07-12T00:00:00Z","status":"active"},
    {"id":"topology:ai:advanced_packaging_to_ai_server","industry_chain_key":"industry_chain:ai_compute_infrastructure","from_chain_node_key":"chain_node:advanced_packaging","to_chain_node_key":"chain_node:ai_server","relation_type":"supplies_to","evidence_note":"完成logic与HBM集成的封装计算组件进入AI服务器；服务器集成交叉来源仍待补。","source_name":"TSMC CoWoS; NVIDIA MGX","source_url":"https://www.nvidia.com/en-us/data-center/products/mgx/","verified_at":"2026-07-12T00:00:00Z","status":"active"},
    {"id":"topology:ai:scale_up_interconnect_to_ai_server","industry_chain_key":"industry_chain:ai_compute_infrastructure","from_chain_node_key":"chain_node:scale_up_interconnect","to_chain_node_key":"chain_node:ai_server","relation_type":"supplies_to","evidence_note":"机架或服务器scale-up fabric。","source_name":"NVIDIA NVLink","source_url":"https://www.nvidia.com/en-eu/data-center/nvlink/","verified_at":"2026-07-12T00:00:00Z","status":"active"},
    {"id":"topology:ai:data_center_networking_to_data_center","industry_chain_key":"industry_chain:ai_compute_infrastructure","from_chain_node_key":"chain_node:data_center_networking","to_chain_node_key":"chain_node:data_center","relation_type":"supplies_to","evidence_note":"网络是数据中心系统组成。","source_name":"NVIDIA Data Center Architecture","source_url":"https://docs.nvidia.com/ncx/ncp-software-reference-guide/latest/data-center-architecture.html","verified_at":"2026-07-12T00:00:00Z","status":"active"},
    {"id":"topology:ai:optical_interconnect_to_networking","industry_chain_key":"industry_chain:ai_compute_infrastructure","from_chain_node_key":"chain_node:optical_interconnect","to_chain_node_key":"chain_node:data_center_networking","relation_type":"supplies_to","evidence_note":"光链路承载网络互连；OIF或IEEE标准来源仍待补。","source_name":"NVIDIA Data Center Architecture","source_url":"https://docs.nvidia.com/ncx/ncp-software-reference-guide/latest/data-center-architecture.html","verified_at":"2026-07-12T00:00:00Z","status":"active"},
    {"id":"topology:ai:storage_to_data_center","industry_chain_key":"industry_chain:ai_compute_infrastructure","from_chain_node_key":"chain_node:ai_storage_system","to_chain_node_key":"chain_node:data_center","relation_type":"supplies_to","evidence_note":"存储是数据中心组成；独立交叉来源仍待补。","source_name":"NVIDIA Data Center Architecture","source_url":"https://docs.nvidia.com/ncx/ncp-software-reference-guide/latest/data-center-architecture.html","verified_at":"2026-07-12T00:00:00Z","status":"active"},
    {"id":"topology:ai:rack_power_to_ai_server","industry_chain_key":"industry_chain:ai_compute_infrastructure","from_chain_node_key":"chain_node:rack_power_system","to_chain_node_key":"chain_node:ai_server","relation_type":"supplies_to","evidence_note":"机架供电系统向IT设备转换并分配电力。","source_name":"Open Compute Project Rack and Power","source_url":"https://www.opencompute.org/index.php/community/rack-and-power","verified_at":"2026-07-12T00:00:00Z","status":"active"},
    {"id":"topology:ai:data_center_depends_on_power_grid","industry_chain_key":"industry_chain:ai_compute_infrastructure","from_chain_node_key":"chain_node:data_center","to_chain_node_key":"chain_node:power_grid","relation_type":"depends_on","evidence_note":"数据中心设施依赖外部并网与供电基础设施。","source_name":"IEA Energy and AI","source_url":"https://www.iea.org/reports/energy-and-ai/energy-demand-from-ai","verified_at":"2026-07-12T00:00:00Z","status":"active"},
    {"id":"topology:ai:ai_server_depends_on_liquid_cooling","industry_chain_key":"industry_chain:ai_compute_infrastructure","from_chain_node_key":"chain_node:ai_server","to_chain_node_key":"chain_node:liquid_cooling_system","relation_type":"depends_on","evidence_note":"高功率密度AI系统对液冷热管理的适用范围需按具体平台核验。","source_name":"NVIDIA MGX; ASHRAE","source_url":"https://www.ashrae.org/technical-resources/bookstore/datacom-series","verified_at":"2026-07-12T00:00:00Z","status":"active"},
    {"id":"topology:semi:eda_to_design","industry_chain_key":"industry_chain:semiconductor_manufacturing","from_chain_node_key":"chain_node:eda","to_chain_node_key":"chain_node:integrated_circuit_design","relation_type":"supplies_to","evidence_note":"EDA工具向集成电路设计活动提供设计、验证和实现能力。","source_name":"Synopsys Silicon Design","source_url":"https://www.synopsys.com/silicon-design.html","verified_at":"2026-07-12T00:00:00Z","status":"active"},
    {"id":"topology:semi:design_to_wafer_fabrication","industry_chain_key":"industry_chain:semiconductor_manufacturing","from_chain_node_key":"chain_node:integrated_circuit_design","to_chain_node_key":"chain_node:wafer_fabrication","relation_type":"supplies_to","evidence_note":"设计制造准备数据作为晶圆制造输入；foundry官方流程来源仍待补。","source_name":"Synopsys Silicon Design","source_url":"https://www.synopsys.com/silicon-design.html","verified_at":"2026-07-12T00:00:00Z","status":"active"},
    {"id":"topology:semi:wafer_material_to_fab","industry_chain_key":"industry_chain:semiconductor_manufacturing","from_chain_node_key":"chain_node:semiconductor_silicon_wafer","to_chain_node_key":"chain_node:wafer_fabrication","relation_type":"supplies_to","evidence_note":"半导体硅片是晶圆制造衬底。","source_name":"SEMI Manufacturing Process","source_url":"https://www.semi.org/en/ehs_PFAS/mfg_markets_overview","verified_at":"2026-07-12T00:00:00Z","status":"active"},
    {"id":"topology:semi:photoresist_to_fab","industry_chain_key":"industry_chain:semiconductor_manufacturing","from_chain_node_key":"chain_node:photoresist","to_chain_node_key":"chain_node:wafer_fabrication","relation_type":"supplies_to","evidence_note":"光刻胶是光刻材料输入；具体材料标准仍待补。","source_name":"SEMI Manufacturing Process","source_url":"https://www.semi.org/en/ehs_PFAS/mfg_markets_overview","verified_at":"2026-07-12T00:00:00Z","status":"active"},
    {"id":"topology:semi:gases_to_fab","industry_chain_key":"industry_chain:semiconductor_manufacturing","from_chain_node_key":"chain_node:electronic_specialty_gases","to_chain_node_key":"chain_node:wafer_fabrication","relation_type":"supplies_to","evidence_note":"电子特气是多项晶圆工艺材料输入；纯度标准仍待补。","source_name":"SEMI Manufacturing Process","source_url":"https://www.semi.org/en/ehs_PFAS/mfg_markets_overview","verified_at":"2026-07-12T00:00:00Z","status":"active"},
    {"id":"topology:semi:lithography_to_fab","industry_chain_key":"industry_chain:semiconductor_manufacturing","from_chain_node_key":"chain_node:lithography_machine","to_chain_node_key":"chain_node:wafer_fabrication","relation_type":"supplies_to","evidence_note":"光刻系统向晶圆制造提供图形转移设备能力。","source_name":"ASML Products","source_url":"https://www.asml.com/en/products","verified_at":"2026-07-12T00:00:00Z","status":"active"},
    {"id":"topology:semi:deposition_to_fab","industry_chain_key":"industry_chain:semiconductor_manufacturing","from_chain_node_key":"chain_node:deposition_equipment","to_chain_node_key":"chain_node:wafer_fabrication","relation_type":"supplies_to","evidence_note":"沉积设备向晶圆制造提供薄膜形成能力。","source_name":"Applied Materials Products","source_url":"https://www.appliedmaterials.com/eu/en/semiconductor/products.html","verified_at":"2026-07-12T00:00:00Z","status":"active"},
    {"id":"topology:semi:etch_to_fab","industry_chain_key":"industry_chain:semiconductor_manufacturing","from_chain_node_key":"chain_node:etch_equipment","to_chain_node_key":"chain_node:wafer_fabrication","relation_type":"supplies_to","evidence_note":"刻蚀设备向晶圆制造提供材料移除能力。","source_name":"Applied Materials Products","source_url":"https://www.appliedmaterials.com/eu/en/semiconductor/products.html","verified_at":"2026-07-12T00:00:00Z","status":"active"},
    {"id":"topology:semi:implant_to_fab","industry_chain_key":"industry_chain:semiconductor_manufacturing","from_chain_node_key":"chain_node:ion_implantation_equipment","to_chain_node_key":"chain_node:wafer_fabrication","relation_type":"supplies_to","evidence_note":"离子注入设备向晶圆制造提供掺杂能力。","source_name":"Applied Materials Products","source_url":"https://www.appliedmaterials.com/eu/en/semiconductor/products.html","verified_at":"2026-07-12T00:00:00Z","status":"active"},
    {"id":"topology:semi:cmp_to_fab","industry_chain_key":"industry_chain:semiconductor_manufacturing","from_chain_node_key":"chain_node:cmp_equipment","to_chain_node_key":"chain_node:wafer_fabrication","relation_type":"supplies_to","evidence_note":"CMP设备向晶圆制造提供平坦化能力。","source_name":"Applied Materials Products","source_url":"https://www.appliedmaterials.com/eu/en/semiconductor/products.html","verified_at":"2026-07-12T00:00:00Z","status":"active"},
    {"id":"topology:semi:inspection_to_fab","industry_chain_key":"industry_chain:semiconductor_manufacturing","from_chain_node_key":"chain_node:metrology_inspection_equipment","to_chain_node_key":"chain_node:wafer_fabrication","relation_type":"supplies_to","evidence_note":"量测和检测设备向晶圆制造提供工艺控制与缺陷反馈能力。","source_name":"KLA Wafer Inspection","source_url":"https://bbp.kla.com/","verified_at":"2026-07-12T00:00:00Z","status":"active"},
    {"id":"topology:semi:fab_to_packaging","industry_chain_key":"industry_chain:semiconductor_manufacturing","from_chain_node_key":"chain_node:wafer_fabrication","to_chain_node_key":"chain_node:advanced_packaging","relation_type":"supplies_to","evidence_note":"前道制造完成的die进入先进封装。","source_name":"TSMC 2024 Annual Report","source_url":"https://investor.tsmc.com/static/annualReports/2024/english/ebook/files/basic-html/page102.html","verified_at":"2026-07-12T00:00:00Z","status":"active"},
    {"id":"topology:semi:packaging_to_testing","industry_chain_key":"industry_chain:semiconductor_manufacturing","from_chain_node_key":"chain_node:advanced_packaging","to_chain_node_key":"chain_node:semiconductor_testing","relation_type":"supplies_to","evidence_note":"封装后器件进入测试；测试流程权威资料仍待补。","source_name":"TSMC CoWoS; SEMI","source_url":"https://3dfabric.tsmc.com/english/dedicatedFoundry/technology/cowos.htm","verified_at":"2026-07-12T00:00:00Z","status":"active"},
    {"id":"topology:semi:testing_to_integrated_circuit","industry_chain_key":"industry_chain:semiconductor_manufacturing","from_chain_node_key":"chain_node:semiconductor_testing","to_chain_node_key":"chain_node:integrated_circuit","relation_type":"supplies_to","evidence_note":"测试合格后形成可交付集成电路产品；测试标准仍待补。","source_name":"SEMI Manufacturing Process","source_url":"https://www.semi.org/en/ehs_PFAS/mfg_markets_overview","verified_at":"2026-07-12T00:00:00Z","status":"active"}
  ],
  "industry_chain_physical_constraints": [
    {"id":"constraint:ai:data_center:power_capacity","industry_chain_key":"industry_chain:ai_compute_infrastructure","chain_node_key":"chain_node:data_center","constraint_type":"power_capacity","mechanism":"IT与冷却功率密度提升增加设施供电需求。","physical_limit_note":"局部电网与站点可用功率限制部署规模。","mitigation_path":"扩容站点供电、提高能效或调整选址。","source_name":"IEA Energy and AI","source_url":"https://www.iea.org/reports/energy-and-ai/energy-demand-from-ai","verified_at":"2026-07-12T00:00:00Z","review_status":"approved","status":"active","generated_by_ai":true,"approved_by_human":true},
    {"id":"constraint:ai:data_center:infrastructure_access","industry_chain_key":"industry_chain:ai_compute_infrastructure","chain_node_key":"chain_node:data_center","constraint_type":"infrastructure_access","mechanism":"数据中心上线依赖物理并网和供电设施接入。","physical_limit_note":"接入容量与物理建设时序限制上线。","mitigation_path":"新建或扩建连接设施。","source_name":"IEA Energy and AI Executive Summary","source_url":"https://www.iea.org/reports/energy-and-ai/executive-summary","verified_at":"2026-07-13T00:00:00Z","review_status":"approved","status":"active","generated_by_ai":true,"approved_by_human":true},
    {"id":"constraint:ai:advanced_packaging:packaging_density","industry_chain_key":"industry_chain:ai_compute_infrastructure","chain_node_key":"chain_node:advanced_packaging","constraint_type":"packaging_density","mechanism":"logic与HBM集成受interposer面积和互连密度限制。","physical_limit_note":"封装尺寸与密度构成工程边界。","mitigation_path":"更大interposer或3D integration。","source_name":"TSMC CoWoS","source_url":"https://3dfabric.tsmc.com/english/dedicatedFoundry/technology/cowos.htm","verified_at":"2026-07-12T00:00:00Z","review_status":"approved","status":"active","generated_by_ai":true,"approved_by_human":true},
    {"id":"constraint:semi:advanced_packaging:reliability","industry_chain_key":"industry_chain:semiconductor_manufacturing","chain_node_key":"chain_node:advanced_packaging","constraint_type":"reliability","mechanism":"高密度互连和热机械应力需要可靠性验证。","physical_limit_note":"封装可靠性是交付边界。","mitigation_path":"材料、结构和测试改进。","source_name":"TSMC/ECTC Reliability Evaluation of a CoWoS-enabled 3D IC Package","source_url":"https://3dfabric.tsmc.com/schinese/dedicatedFoundry/technology/del/cowos_publications_ECTC2013.htm","verified_at":"2026-07-13T00:00:00Z","review_status":"approved","status":"active","generated_by_ai":true,"approved_by_human":true}
  ]
}
